cytimes/utils.pyi
cytimes/delta.pxd
cytimes/parser.pyi
cytimes/utils.py
cytimes/delta.pyi
cytimes/errors.cpython-310-x86_64-linux-gnu.so
cytimes/pddt.py
cytimes/utils.cpython-310-x86_64-linux-gnu.so
cytimes/errors.c
cytimes/pddt.pyi
cytimes/pydt.cpython-310-x86_64-linux-gnu.so
cytimes/utils.pxd
cytimes/pydt.c
cytimes/pydt.pxd
cytimes/pydt.pyi
cytimes/pddt.c
cytimes/pddt.cpython-310-x86_64-linux-gnu.so
cytimes/parser.c
cytimes/parser.cpython-310-x86_64-linux-gnu.so
cytimes/delta.cpython-310-x86_64-linux-gnu.so
cytimes/parser.pxd
cytimes/utils.c
cytimes/pydt.py
cytimes/delta.py
cytimes/parser.py
cytimes/pddt.pxd
cytimes/errors.pxd
cytimes/delta.c
cytimes/__init__.pxd
cytimes/__init__.py
cytimes/errors.py
cytimes-3.0.3.dist-info/WHEEL
cytimes-3.0.3.dist-info/top_level.txt
cytimes-3.0.3.dist-info/METADATA
cytimes-3.0.3.dist-info/RECORD
cytimes-3.0.3.dist-info/licenses/LICENSE
