Metadata-Version: 2.4
Name: cytimes
Version: 3.0.3
Summary: Make working with datetimes in Python simpler and more powerful.
Home-page: https://github.com/AresJef/cyTimes
Author: Jiefu Chen
Author-email: keppa1991@163.com
License: MIT license, Apache License 2.0, BSD 3-Clause
Keywords: cytimes,parser,datetime,pandas,Series,DatetimeIndex
Classifier: Programming Language :: Python :: 3
Classifier: Operating System :: Unix
Classifier: Operating System :: MacOS :: MacOS X
Classifier: Operating System :: Microsoft :: Windows
Requires-Python: >=3.10
License-File: LICENSE
Requires-Dist: babel>=2.12.0
Requires-Dist: numpy>=1.25.2
Requires-Dist: pandas>=2.1.0
Requires-Dist: python-dateutil>=2.8.2
Requires-Dist: typing-extensions>=4.9.0
Dynamic: license-file
